{
  "products": [
    {
      "id": "b06a",
      "imgUrl": "https://m.naturestore.co.kr/data/goods/21/02/08/1000004285/1000004285_detail_02.jpg",
      "categoryName": "shoes",
      "pdDetail": "Lorem ipsum dolor sit, amet consectetur adipisicing elit. Fugit, illo incidunt. Facere perspiciatis doloribus asperiores explicabo fugiat nihil, optio aut, eum harum ad porro commodi",
      "pdName": "Black shoes",
      "pdPrice": "13,000",
      "pdQuantity": "30개",
      "pdSize": "250",
      "pdStat": "호잇!",
      "userEmail": "wlseldrnt@naver.com"
    },
    {
      "id": "0481",
      "imgUrl": "https://arena.co.kr/web/product/big/shop1_3957f71f3f42e557517d62f8507202e8.png",
      "categoryName": "outer",
      "pdDetail": "Lorem ipsum dolor sit, amet consectetur adipisicing elit. Fugit, illo incidunt. Facere perspiciatis doloribus asperiores explicabo fugiat nihil, optio aut, eum harum ad porro commodi",
      "pdPrice": "20,000",

      "pdName": "Good Outer",
      "pdQuantity": "500",
      "pdSize": "xl",
      "pdStat": "str",
      "userEmail": "wlseldrnt@naver.com"
    },

    {
      "id": "0587",
      "imgUrl": "https://covernat.net/web/product/medium/20230922/CO2304KT64IV_1.jpg",
      "categoryName": "outer",
      "pdDetail": "Lorem ipsum dolor sit, amet consectetur adipisicing elit. Fugit, illo incidunt. Facere perspiciatis doloribus asperiores explicabo fugiat nihil, optio aut, eum harum ad porro commodi",
      "pdPrice": "20,000",

      "pdName": "Good Outer",
      "pdQuantity": "500",
      "pdSize": "xl",
      "pdStat": "str",
      "userEmail": "wlseldrnt@naver.com"
    },
    {
      "id": "223e",
      "imgUrl": "https://static-resource.discovery-expedition.com/images/goods/ec/X23FDMTP66036BKS/thnail/6B3DAC3924BE42C09EE6222A29624A59.png/dims/resize/940x1253",
      "categoryName": "pants",
      "pdDetail": "Lorem ipsum dolor sit, amet consectetur adipisicing elit. Fugit, illo incidunt. Facere perspiciatis doloribus asperiores explicabo fugiat nihil, optio aut, eum harum ad porro commodi",
      "pdPrice": "20,000",

      "pdName": "Jogger pants",
      "pdQuantity": "200",
      "pdSize": "xl",
      "pdStat": "luck",
      "userEmail": "wlseldrnt@naver.com"
    },

    {
      "id": "253e",
      "imgUrl": "https://static-resource.discovery-expedition.com/images/goods/ec/X23FDMTP66036BKS/thnail/6B3DAC3924BE42C09EE6222A29624A59.png/dims/resize/940x1253",
      "categoryName": "pants",
      "pdDetail": "Lorem ipsum dolor sit, amet consectetur adipisicing elit. Fugit, illo incidunt. Facere perspiciatis doloribus asperiores explicabo fugiat nihil, optio aut, eum harum ad porro commodi",
      "pdPrice": "20,000",

      "pdName": "Jogger pants",
      "pdQuantity": "200",
      "pdSize": "xl",
      "pdStat": "luck",
      "userEmail": "wlseldrnt@naver.com"
    },

    {
      "id": "0487",
      "imgUrl": "https://arena.co.kr/web/product/big/shop1_3957f71f3f42e557517d62f8507202e8.png",
      "categoryName": "outer",
      "pdDetail": "Lorem ipsum dolor sit, amet consectetur adipisicing elit. Fugit, illo incidunt. Facere perspiciatis doloribus asperiores explicabo fugiat nihil, optio aut, eum harum ad porro commodi",
      "pdPrice": "20,000",

      "pdName": "Good Outer",
      "pdQuantity": "500",
      "pdSize": "xl",
      "pdStat": "str",
      "userEmail": "wlseldrnt@naver.com"
    },
    {
      "id": "b02a",
      "imgUrl": "https://m.naturestore.co.kr/data/goods/21/02/08/1000004285/1000004285_detail_02.jpg",
      "categoryName": "shoes",
      "pdDetail": "Lorem ipsum dolor sit, amet consectetur adipisicing elit. Fugit, illo incidunt. Facere perspiciatis doloribus asperiores explicabo fugiat nihil, optio aut, eum harum ad porro commodi",
      "pdName": "Black shoes",
      "pdPrice": "13,000",
      "pdQuantity": "30개",
      "pdSize": "250",
      "pdStat": "호잇!",
      "userEmail": "wlseldrnt@naver.com"
    },
    {
      "id": "0488",
      "imgUrl": "https://covernat.net/web/product/medium/20230922/CO2304KT64IV_1.jpg",
      "categoryName": "outer",
      "pdDetail": "Lorem ipsum dolor sit, amet consectetur adipisicing elit. Fugit, illo incidunt. Facere perspiciatis doloribus asperiores explicabo fugiat nihil, optio aut, eum harum ad porro commodi",
      "pdPrice": "20,000",

      "pdName": "Good Outer",
      "pdQuantity": "500",
      "pdSize": "xl",
      "pdStat": "str",
      "userEmail": "wlseldrnt@naver.com"
    },
    {
      "id": "04818",
      "imgUrl": "https://covernat.net/web/product/medium/20230922/CO2304KT64IV_1.jpg",
      "categoryName": "outer",
      "pdDetail": "Lorem ipsum dolor sit, amet consectetur adipisicing elit. Fugit, illo incidunt. Facere perspiciatis doloribus asperiores explicabo fugiat nihil, optio aut, eum harum ad porro commodi",
      "pdPrice": "20,000",

      "pdName": "Good Outer",
      "pdQuantity": "500",
      "pdSize": "xl",
      "pdStat": "str",
      "userEmail": "wlseldrnt@naver.com"
    },
    {
      "id": "b025",
      "imgUrl": "https://m.naturestore.co.kr/data/goods/21/02/08/1000004285/1000004285_detail_02.jpg",
      "categoryName": "shoes",
      "pdDetail": "Lorem ipsum dolor sit, amet consectetur adipisicing elit. Fugit, illo incidunt. Facere perspiciatis doloribus asperiores explicabo fugiat nihil, optio aut, eum harum ad porro commodi",

      "pdName": "Black shoes",
      "pdPrice": "13,000",
      "pdQuantity": "30개",
      "pdSize": "250",
      "pdStat": "호잇!",
      "userEmail": "wlseldrnt@naver.com"
    }
  ]
}
